LICENSE
README.md
oyabun/__init__.py
oyabun/bot.py
oyabun/telegram/__init__.py
oyabun/telegram/base.py
oyabun/telegram/entities.py
oyabun/telegram/requests.py
oyabun/telegram/responses.py
oyabun/version.py
oyabun-2022.12.12.dist-info/METADATA
oyabun-2022.12.12.dist-info/WHEEL
oyabun-2022.12.12.dist-info/LICENSE
oyabun-2022.12.12.dist-info/RECORD
