Metadata-Version: 2.1
Name: oyabun
Version: 2022.12.12
Summary: Telegram library with strict API
Home-page: https://github.com/tgrx/oyabun
License: MIT
Keywords: telegram
Author: Alexander Sidorov
Author-email: alexander@sidorov.dev
Maintainer: Alexander Sidorov
Maintainer-email: alexander@sidorov.dev
Requires-Python: >=3.10,<4.0
Classifier: Development Status :: 5 - Production/Stable
Classifier: Environment :: Console
Classifier: Intended Audience :: Developers
Classifier: Intended Audience :: Telecommunications Industry
Classifier: License :: OSI Approved :: MIT License
Classifier: Natural Language :: English
Classifier: Operating System :: MacOS :: MacOS X
Classifier: Operating System :: POSIX :: Linux
Classifier: Programming Language :: Python
Classifier: Programming Language :: Python :: 3
Classifier: Programming Language :: Python :: 3.10
Classifier: Programming Language :: Python :: 3.11
Classifier: Programming Language :: Python :: 3
Classifier: Programming Language :: Python :: 3.10
Classifier: Programming Language :: Python :: Implementation :: CPython
Classifier: Topic :: Communications :: Chat
Classifier: Topic :: Software Development :: Libraries :: Application Frameworks
Requires-Dist: aiohttp[speedups] (>=3.8.1,<4.0.0)
Requires-Dist: orjson (>=3.7.11,<4.0.0)
Requires-Dist: pydantic (>=1.9.1,<2.0.0)
Project-URL: Repository, https://github.com/tgrx/oyabun
